pyxmlhandler.cpython-310-x86_64-linux-gnu.so
xmlpydict/__init__.py
xmlpydict-0.0.11.dist-info/METADATA
xmlpydict-0.0.11.dist-info/WHEEL
xmlpydict-0.0.11.dist-info/top_level.txt
xmlpydict-0.0.11.dist-info/RECORD
xmlpydict-0.0.11.dist-info/licenses/LICENSE
