Metadata-Version: 2.4
Name: xmlpydict
Version: 0.0.11
Summary: xml to dictionary tool for python
Author-email: Matthew Taylor <matthew.taylor.andre@gmail.com>
Project-URL: Homepage, https://github.com/MatthewAndreTaylor/xml-to-pydict
Keywords: xml,dictionary
Classifier: Development Status :: 3 - Alpha
Classifier: Intended Audience :: Developers
Classifier: License :: OSI Approved :: MIT License
Classifier: Programming Language :: Python :: 3
Classifier: Programming Language :: Python :: 3 :: Only
Classifier: Programming Language :: Python :: 3.8
Classifier: Programming Language :: Python :: 3.9
Classifier: Programming Language :: Python :: 3.10
Classifier: Programming Language :: Python :: 3.11
Classifier: Programming Language :: Python :: Implementation :: CPython
Classifier: Topic :: Software Development :: Libraries :: Python Modules
Classifier: Topic :: Text Processing :: Markup :: XML
Requires-Python: >=3.7
License-File: LICENSE
Provides-Extra: tests
Requires-Dist: pytest; extra == "tests"
Requires-Dist: requests; extra == "tests"
Dynamic: license-file
